mp4_tools/ConcatVideos.py
mp4_tools/Convert.py
mp4_tools/__init__.py
mp4_tools/rename.py
mp4_tools-0.0.2.dist-info/METADATA
mp4_tools-0.0.2.dist-info/WHEEL
mp4_tools-0.0.2.dist-info/top_level.txt
mp4_tools-0.0.2.dist-info/RECORD
