Metadata-Version: 2.1
Name: mp4_tools
Version: 0.0.2
Author: Happy
Author-email: zoujian49@126.com
License: MIT
Keywords: mp4 tools
Requires-Dist: coloredlogs
Requires-Dist: ffmpeg-python
Requires-Dist: ffmpy
Requires-Dist: ffmpeg
